shy/__init__.py
shy/utils.py
shy-0.2.4.dist-info/METADATA
shy-0.2.4.dist-info/WHEEL
shy-0.2.4.dist-info/top_level.txt
shy-0.2.4.dist-info/RECORD
